m3uragen/__init__.py
m3uragen/image.py
m3uragen/m3u.py
m3uragen/main.py
m3uragen/romset.py
m3uragen/software.py
m3uragen-1.1.0.dist-info/LICENSE
m3uragen-1.1.0.dist-info/METADATA
m3uragen-1.1.0.dist-info/WHEEL
m3uragen-1.1.0.dist-info/entry_points.txt
m3uragen-1.1.0.dist-info/top_level.txt
m3uragen-1.1.0.dist-info/RECORD
