Metadata-Version: 2.1
Name: m3uragen
Version: 1.1.0
Summary: Generate M3U playlists from multi images software romsets for use with RetroArch 
Home-page: https://github.com/TiBeN/m3uragen
Author: Benjamin Legendre
Author-email: jeff58888@hotmail.com
License: UNKNOWN
Platform: UNKNOWN
Classifier: Programming Language :: Python :: 3
Classifier: License :: OSI Approved :: MIT License
Classifier: Operating System :: OS Independent
Requires-Python: >=3.6
